scripts/conjugation_xml_filter.py
tests/test_conjugator.py
tests/test_localization.py
tests/test_mlconjug.py
tests/test_string_utils.py
tests/test_type_annotations.py
tests/test_inflectors/test_inflector_ca.py
tests/test_inflectors/test_inflector_es.py
tests/test_inflectors/test_inflector_fr.py
tests/test_inflectors/test_inflector_it.py
tests/test_inflectors/test_inflector_pt.py
tests/test_inflectors/test_inflector_ro.py
tests/test_parser/test_conjugation_template.py
tests/test_parser/test_tense_and_person.py
tests/test_parser/test_verbs_parser.py
verbecc/__init__.py
verbecc/__pycache__/__init__.cpython-311.pyc
verbecc/data/models/dummy-file-because-github-doesnt-like-large-files.md
verbecc/data/xml/conjugations/conjugations-ca.xml
verbecc/data/xml/conjugations/conjugations-es.xml
verbecc/data/xml/conjugations/conjugations-fr.xml
verbecc/data/xml/conjugations/conjugations-it.xml
verbecc/data/xml/conjugations/conjugations-pt.xml
verbecc/data/xml/conjugations/conjugations-ro.xml
verbecc/data/xml/verbs/verbs-ca.xml
verbecc/data/xml/verbs/verbs-es.xml
verbecc/data/xml/verbs/verbs-fr.xml
verbecc/data/xml/verbs/verbs-it.xml
verbecc/data/xml/verbs/verbs-pt.xml
verbecc/data/xml/verbs/verbs-ro.xml
verbecc/src/__init__.py
verbecc/src/__pycache__/__init__.cpython-311.pyc
verbecc/src/conjugator/__init__.py
verbecc/src/conjugator/conjugation_object.py
verbecc/src/conjugator/conjugator.py
verbecc/src/conjugator/__pycache__/__init__.cpython-311.pyc
verbecc/src/conjugator/__pycache__/conjugation_object.cpython-311.pyc
verbecc/src/conjugator/__pycache__/conjugator.cpython-311.pyc
verbecc/src/defs/__init__.py
verbecc/src/defs/__pycache__/__init__.cpython-311.pyc
verbecc/src/defs/constants/__init__.py
verbecc/src/defs/constants/config.py
verbecc/src/defs/constants/grammar_defines.py
verbecc/src/defs/constants/localization.py
verbecc/src/defs/constants/__pycache__/__init__.cpython-311.pyc
verbecc/src/defs/constants/__pycache__/config.cpython-311.pyc
verbecc-1.11.5.dist-info/licenses/LICENSE.txt
verbecc-1.11.5.dist-info/METADATA
verbecc-1.11.5.dist-info/WHEEL
verbecc-1.11.5.dist-info/entry_points.txt
verbecc-1.11.5.dist-info/top_level.txt
verbecc-1.11.5.dist-info/RECORD
