Metadata-Version: 2.4
Name: verbecc
Version: 1.11.5
Summary: Verbs Completely Conjugated: machine learning conjugator for Catalan, French, Italian, Portuguese, Romanian and Spanish
Author-email: Brett Tolbert <bretttolbert@gmail.com>
Maintainer-email: Brett Tolbert <bretttolbert@gmail.com>
License:                    GNU LESSER GENERAL PUBLIC LICENSE
Project-URL: Homepage, https://github.com/bretttolbert/verbecc
Project-URL: Documentation, https://github.com/bretttolbert/verbecc
Project-URL: Repository, https://github.com/bretttolbert/verbecc.git
Project-URL: Bug Tracker, https://github.com/bretttolbert/verbecc/issues
Project-URL: Changelog, https://github.com/bretttolbert/verbecc/blob/master/CHANGELOG.md
Keywords: verb,,conjugator,conjugation,Catalan,French,Italian,Portuguese,Romanian,Spanish
Classifier: Development Status :: 5 - Production/Stable
Classifier: Topic :: Software Development :: Libraries :: Python Modules
Classifier: Topic :: Text Processing :: Linguistic
Classifier: Topic :: Education
Classifier: Topic :: Scientific/Engineering :: Artificial Intelligence
Classifier: Topic :: Utilities
Classifier: Intended Audience :: Developers
Classifier: Intended Audience :: End Users/Desktop
Classifier: Intended Audience :: Education
Classifier: Intended Audience :: Science/Research
Classifier: License :: OSI Approved :: GNU Lesser General Public License v3 (LGPLv3)
Classifier: Natural Language :: Catalan
Classifier: Natural Language :: French
Classifier: Natural Language :: Italian
Classifier: Natural Language :: Portuguese
Classifier: Natural Language :: Romanian
Classifier: Natural Language :: Spanish
Classifier: Operating System :: OS Independent
Classifier: Programming Language :: Python :: 3
Classifier: Programming Language :: Python :: 3.9
Classifier: Programming Language :: Python :: 3.10
Classifier: Programming Language :: Python :: 3.11
Classifier: Programming Language :: Python :: 3.12
Classifier: Programming Language :: Python :: 3.13
Classifier: Programming Language :: Python :: 3.14
Requires-Python: >=3.9
License-File: LICENSE.txt
Requires-Dist: cython>=3.1.4
Requires-Dist: importlib_resources==6.4.5; python_version < "3.13"
Requires-Dist: importlib_resources==6.5.2; python_version >= "3.13"
Requires-Dist: lxml>=6.0.2
Requires-Dist: lxml-stubs>=0.5.1
Requires-Dist: numpy==1.6.1; python_version < "3.11"
Requires-Dist: numpy==2.3.3; python_version >= "3.11"
Requires-Dist: scikit-learn==1.6.1; python_version < "3.10"
Requires-Dist: scikit-learn==1.7.2; python_version >= "3.10"
Requires-Dist: scipy==1.13.1; python_version < "3.10"
Requires-Dist: scipy==1.15.3; python_version == "3.10"
Requires-Dist: scipy==1.16.2; python_version >= "3.11"
Requires-Dist: backports.strenum<2.0,>=1.3.1; python_version < "3.11"
Dynamic: license-file
